[
  {
    "id": "1",
    "word": "merhaba",
    "pronunciation": "mehr-HAH-bah",
    "meaning": "hello",
    "part_of_speech": "interjection",
    "difficulty": "easy",
    "lesson_no": 1,
    "when_to_say": "When greeting someone casually.",
    "example": "Merhaba! Nasılsın? (Hello! How are you?)"
  },
  {
    "id": "2",
    "word": "günaydın",
    "pronunciation": "goo-nigh-dun",
    "meaning": "good morning",
    "part_of_speech": "interjection",
    "difficulty": "easy",
    "lesson_no": 1,
    "when_to_say": "When greeting someone in the morning.",
    "example": "Günaydın! Bugün hava güzel. (Good morning! The weather is nice today.)"
  },
  {
    "id": "3",
    "word": "iyi günler",
    "pronunciation": "ee-yee gun-ler",
    "meaning": "good afternoon",
    "part_of_speech": "interjection",
    "difficulty": "easy",
    "lesson_no": 1,
    "when_to_say": "When greeting or parting in the afternoon.",
    "example": "İyi günler dilerim! (I wish you a good day!)"
  },
  {
    "id": "4",
    "word": "iyi akşamlar",
    "pronunciation": "ee-yee ahk-sham-lar",
    "meaning": "good evening",
    "part_of_speech": "interjection",
    "difficulty": "easy",
    "lesson_no": 1,
    "when_to_say": "When greeting or parting in the evening.",
    "example": "İyi akşamlar! Görüşürüz. (Good evening! See you later.)"
  },
  {
    "id": "5",
    "word": "hoşça kal",
    "pronunciation": "hosh-cha-kahl",
    "meaning": "goodbye",
    "part_of_speech": "interjection",
    "difficulty": "easy",
    "lesson_no": 1,
    "when_to_say": "When leaving someone and saying goodbye.",
    "example": "Hoşça kal! Yarın görüşürüz. (Goodbye! See you tomorrow.)"
  },
  {
    "id": "6",
    "word": "teşekkür ederim",
    "pronunciation": "teh-shehk-kur eh-deh-reem",
    "meaning": "thank you",
    "part_of_speech": "phrase",
    "difficulty": "easy",
    "lesson_no": 1,
    "when_to_say": "When expressing gratitude.",
    "example": "Teşekkür ederim! Yardımınız için. (Thank you! For your help.)"
  },
  {
    "id": "7",
    "word": "lütfen",
    "pronunciation": "loot-fen",
    "meaning": "please",
    "part_of_speech": "adverb",
    "difficulty": "easy",
    "lesson_no": 1,
    "when_to_say": "When politely requesting something.",
    "example": "Lütfen kapıyı açar mısınız? (Please open the door.)"
  },
  {
    "id": "8",
    "word": "evet",
    "pronunciation": "eh-vet",
    "meaning": "yes",
    "part_of_speech": "adverb",
    "difficulty": "easy",
    "lesson_no": 1,
    "when_to_say": "When affirming or agreeing.",
    "example": "Evet, bu doğru. (Yes, that is correct.)"
  },
  {
    "id": "9",
    "word": "hayır",
    "pronunciation": "hah-yur",
    "meaning": "no",
    "part_of_speech": "adverb",
    "difficulty": "easy",
    "lesson_no": 1,
    "when_to_say": "When denying or disagreeing.",
    "example": "Hayır, bunu istemiyorum. (No, I don't want this.)"
  },
  {
    "id": "10",
    "word": "özür dilerim",
    "pronunciation": "uh-zoor dee-leh-reem",
    "meaning": "I'm sorry",
    "part_of_speech": "phrase",
    "difficulty": "easy",
    "lesson_no": 1,
    "when_to_say": "When apologizing.",
    "example": "Özür dilerim, geç kaldım. (I'm sorry, I'm late.)"
  },
  {
    "id": "11",
    "word": "aşk",
    "pronunciation": "ahshk",
    "meaning": "love",
    "part_of_speech": "noun",
    "difficulty": "medium",
    "lesson_no": 2,
    "when_to_say": "When talking about romantic feelings.",
    "example": "Aşk, hayatı güzelleştirir. (Love makes life beautiful.)"
  },
  {
    "id": "12",
    "word": "arkadaş",
    "pronunciation": "ahr-kah-dahsh",
    "meaning": "friend",
    "part_of_speech": "noun",
    "difficulty": "easy",
    "lesson_no": 2,
    "when_to_say": "When referring to a companion.",
    "example": "Bu benim arkadaşım Ali. (This is my friend Ali.)"
  },
  {
    "id": "13",
    "word": "mutlu",
    "pronunciation": "moot-loo",
    "meaning": "happy",
    "part_of_speech": "adjective",
    "difficulty": "easy",
    "lesson_no": 2,
    "when_to_say": "When describing a joyful state.",
    "example": "Bugün çok mutluyum. (I am very happy today.)"
  },
  {
    "id": "14",
    "word": "üzgün",
    "pronunciation": "ooz-goon",
    "meaning": "sad",
    "part_of_speech": "adjective",
    "difficulty": "easy",
    "lesson_no": 2,
    "when_to_say": "When describing a sorrowful state.",
    "example": "O bugün çok üzgün. (She is very sad today.)"
  },
  {
    "id": "15",
    "word": "güzel",
    "pronunciation": "goo-zehl",
    "meaning": "beautiful",
    "part_of_speech": "adjective",
    "difficulty": "easy",
    "lesson_no": 2,
    "when_to_say": "When describing something aesthetically pleasing.",
    "example": "Manzara çok güzel. (The view is very beautiful.)"
  },
  {
    "id": "16",
    "word": "çirkin",
    "pronunciation": "cheer-keen",
    "meaning": "ugly",
    "part_of_speech": "adjective",
    "difficulty": "easy",
    "lesson_no": 2,
    "when_to_say": "When describing something unattractive.",
    "example": "Bu tablo çok çirkin. (This painting is very ugly.)"
  },
  {
    "id": "17",
    "word": "büyük",
    "pronunciation": "boo-yook",
    "meaning": "big",
    "part_of_speech": "adjective",
    "difficulty": "easy",
    "lesson_no": 2,
    "when_to_say": "When describing the large size of something.",
    "example": "Bu ev çok büyük. (This house is very big.)"
  },
  {
    "id": "18",
    "word": "küçük",
    "pronunciation": "koo-chook",
    "meaning": "small",
    "part_of_speech": "adjective",
    "difficulty": "easy",
    "lesson_no": 2,
    "when_to_say": "When describing the small size of something.",
    "example": "Küçük bir hediye aldım. (I got a small gift.)"
  },
  {
    "id": "19",
    "word": "iyi",
    "pronunciation": "ee-yee",
    "meaning": "good",
    "part_of_speech": "adjective",
    "difficulty": "easy",
    "lesson_no": 1,
    "when_to_say": "When describing something positive.",
    "example": "Bugün hava çok iyi. (The weather is very good today.)"
  },
  {
    "id": "20",
    "word": "kötü",
    "pronunciation": "koh-too",
    "meaning": "bad",
    "part_of_speech": "adjective",
    "difficulty": "easy",
    "lesson_no": 1,
    "when_to_say": "When describing something negative.",
    "example": "Bu film kötüydü. (This movie was bad.)"
  },

  {
    "id": "21",
    "word": "hızlı",
    "pronunciation": "huhz-luh",
    "meaning": "fast",
    "part_of_speech": "adjective",
    "difficulty": "easy",
    "lesson_no": 3,
    "when_to_say": "When describing something that moves quickly.",
    "example": "Araba çok hızlı gidiyor. (The car is going very fast.)"
  },
  {
    "id": "22",
    "word": "yavaş",
    "pronunciation": "yah-vahsh",
    "meaning": "slow",
    "part_of_speech": "adjective",
    "difficulty": "easy",
    "lesson_no": 3,
    "when_to_say": "When describing something that moves slowly.",
    "example": "Lütfen yavaş konuş. (Please speak slowly.)"
  },
  {
    "id": "23",
    "word": "mutfak",
    "pronunciation": "moot-fahk",
    "meaning": "kitchen",
    "part_of_speech": "noun",
    "difficulty": "easy",
    "lesson_no": 4,
    "when_to_say": "When referring to the cooking area in a home.",
    "example": "Mutfakta yemek yapıyorum. (I am cooking in the kitchen.)"
  },
  {
    "id": "24",
    "word": "banyo",
    "pronunciation": "bahn-yoh",
    "meaning": "bathroom",
    "part_of_speech": "noun",
    "difficulty": "easy",
    "lesson_no": 4,
    "when_to_say": "When referring to the bathroom.",
    "example": "Banyo temiz mi? (Is the bathroom clean?)"
  },
  {
    "id": "25",
    "word": "oturma odası",
    "pronunciation": "oh-toor-mah oh-dah-suh",
    "meaning": "living room",
    "part_of_speech": "noun",
    "difficulty": "easy",
    "lesson_no": 4,
    "when_to_say": "When referring to the main room in a home.",
    "example": "Oturma odasında televizyon izliyoruz. (We are watching TV in the living room.)"
  },
  {
    "id": "26",
    "word": "yatak odası",
    "pronunciation": "yah-tahk oh-dah-suh",
    "meaning": "bedroom",
    "part_of_speech": "noun",
    "difficulty": "easy",
    "lesson_no": 4,
    "when_to_say": "When referring to the sleeping room.",
    "example": "Yatak odasında kitap okuyorum. (I am reading a book in the bedroom.)"
  },
  {
    "id": "27",
    "word": "bahçe",
    "pronunciation": "bah-cheh",
    "meaning": "garden",
    "part_of_speech": "noun",
    "difficulty": "easy",
    "lesson_no": 4,
    "when_to_say": "When referring to the garden area.",
    "example": "Bahçede çiçekler var. (There are flowers in the garden.)"
  },
  {
    "id": "28",
    "word": "kapı",
    "pronunciation": "kah-puh",
    "meaning": "door",
    "part_of_speech": "noun",
    "difficulty": "easy",
    "lesson_no": 4,
    "when_to_say": "When referring to an entryway.",
    "example": "Kapıyı kapatır mısınız? (Can you close the door?)"
  },
  {
    "id": "29",
    "word": "pencere",
    "pronunciation": "pen-jeh-reh",
    "meaning": "window",
    "part_of_speech": "noun",
    "difficulty": "easy",
    "lesson_no": 4,
    "when_to_say": "When referring to a glass opening in a wall.",
    "example": "Pencereyi açabilir misin? (Can you open the window?)"
  },
  {
    "id": "30",
    "word": "masa",
    "pronunciation": "mah-sah",
    "meaning": "table",
    "part_of_speech": "noun",
    "difficulty": "easy",
    "lesson_no": 4,
    "when_to_say": "When referring to a table.",
    "example": "Masada kitap var. (There is a book on the table.)"
  },
  {
    "id": "31",
    "word": "sandalye",
    "pronunciation": "san-dahl-yeh",
    "meaning": "chair",
    "part_of_speech": "noun",
    "difficulty": "easy",
    "lesson_no": 4,
    "when_to_say": "When referring to a chair.",
    "example": "Sandalyeyi masanın yanına koy. (Put the chair next to the table.)"
  },
  {
    "id": "32",
    "word": "yatak",
    "pronunciation": "yah-tahk",
    "meaning": "bed",
    "part_of_speech": "noun",
    "difficulty": "easy",
    "lesson_no": 4,
    "when_to_say": "When referring to a place for sleeping.",
    "example": "Yatağımı sabah topladım. (I made my bed in the morning.)"
  },
  {
    "id": "33",
    "word": "koltuk",
    "pronunciation": "kohl-took",
    "meaning": "sofa",
    "part_of_speech": "noun",
    "difficulty": "easy",
    "lesson_no": 4,
    "when_to_say": "When referring to a sofa or armchair.",
    "example": "Koltuk çok rahat. (The sofa is very comfortable.)"
  },
  {
    "id": "34",
    "word": "halı",
    "pronunciation": "hah-luh",
    "meaning": "carpet",
    "part_of_speech": "noun",
    "difficulty": "easy",
    "lesson_no": 4,
    "when_to_say": "When referring to a carpet or rug.",
    "example": "Halıyı temizlemek gerekiyor. (The carpet needs cleaning.)"
  },
  {
    "id": "35",
    "word": "ayna",
    "pronunciation": "aye-nah",
    "meaning": "mirror",
    "part_of_speech": "noun",
    "difficulty": "easy",
    "lesson_no": 4,
    "when_to_say": "When referring to a reflective surface.",
    "example": "Aynada kendime baktım. (I looked at myself in the mirror.)"
  },
  {
    "id": "36",
    "word": "lamba",
    "pronunciation": "lahm-bah",
    "meaning": "lamp",
    "part_of_speech": "noun",
    "difficulty": "easy",
    "lesson_no": 4,
    "when_to_say": "When referring to a light source.",
    "example": "Lamba bozulmuş. (The lamp is broken.)"
  },
  {
    "id": "37",
    "word": "kitap",
    "pronunciation": "kee-tahp",
    "meaning": "book",
    "part_of_speech": "noun",
    "difficulty": "easy",
    "lesson_no": 5,
    "when_to_say": "When referring to a book.",
    "example": "Bu kitap çok ilginç. (This book is very interesting.)"
  },
  {
    "id": "38",
    "word": "defter",
    "pronunciation": "def-tehr",
    "meaning": "notebook",
    "part_of_speech": "noun",
    "difficulty": "easy",
    "lesson_no": 5,
    "when_to_say": "When referring to a notebook.",
    "example": "Defterime not alıyorum. (I am taking notes in my notebook.)"
  },
  {
    "id": "39",
    "word": "kalem",
    "pronunciation": "kah-lehm",
    "meaning": "pen",
    "part_of_speech": "noun",
    "difficulty": "easy",
    "lesson_no": 5,
    "when_to_say": "When referring to a pen.",
    "example": "Kalemim kırıldı. (My pen broke.)"
  },
  {
    "id": "40",
    "word": "silgi",
    "pronunciation": "seel-gee",
    "meaning": "eraser",
    "part_of_speech": "noun",
    "difficulty": "easy",
    "lesson_no": 5,
    "when_to_say": "When referring to an eraser.",
    "example": "Silgiyi masadan alabilir misin? (Can you take the eraser from the table?)"
  },

  {
    "id": "41",
    "word": "bilgisayar",
    "pronunciation": "beel-gee-sah-yar",
    "meaning": "computer",
    "part_of_speech": "noun",
    "difficulty": "medium",
    "lesson_no": 5,
    "when_to_say": "When referring to a computer.",
    "example": "Bilgisayarım bozuldu. (My computer is broken.)"
  },
  {
    "id": "42",
    "word": "telefon",
    "pronunciation": "teh-leh-fohn",
    "meaning": "phone",
    "part_of_speech": "noun",
    "difficulty": "easy",
    "lesson_no": 5,
    "when_to_say": "When referring to a telephone or smartphone.",
    "example": "Telefonum çalıyor. (My phone is ringing.)"
  },
  {
    "id": "43",
    "word": "saat",
    "pronunciation": "sah-aht",
    "meaning": "clock",
    "part_of_speech": "noun",
    "difficulty": "easy",
    "lesson_no": 5,
    "when_to_say": "When referring to time or a clock.",
    "example": "Saat kaçı gösteriyor? (What time does the clock show?)"
  },
  {
    "id": "44",
    "word": "araba",
    "pronunciation": "ah-rah-bah",
    "meaning": "car",
    "part_of_speech": "noun",
    "difficulty": "easy",
    "lesson_no": 6,
    "when_to_say": "When referring to an automobile.",
    "example": "Yeni bir araba aldık. (We bought a new car.)"
  },
  {
    "id": "45",
    "word": "bisiklet",
    "pronunciation": "bee-seek-leht",
    "meaning": "bicycle",
    "part_of_speech": "noun",
    "difficulty": "easy",
    "lesson_no": 6,
    "when_to_say": "When referring to a bicycle.",
    "example": "Bisikletle sahile gittim. (I went to the beach by bicycle.)"
  },
  {
    "id": "46",
    "word": "tren",
    "pronunciation": "trehn",
    "meaning": "train",
    "part_of_speech": "noun",
    "difficulty": "easy",
    "lesson_no": 6,
    "when_to_say": "When referring to a train.",
    "example": "Tren saat kaçta kalkıyor? (What time does the train leave?)"
  },
  {
    "id": "47",
    "word": "uçak",
    "pronunciation": "oo-chahk",
    "meaning": "airplane",
    "part_of_speech": "noun",
    "difficulty": "medium",
    "lesson_no": 6,
    "when_to_say": "When referring to an airplane.",
    "example": "Uçak çok hızlıdır. (The airplane is very fast.)"
  },
  {
    "id": "48",
    "word": "gemi",
    "pronunciation": "geh-mee",
    "meaning": "ship",
    "part_of_speech": "noun",
    "difficulty": "easy",
    "lesson_no": 6,
    "when_to_say": "When referring to a ship or large boat.",
    "example": "Gemiyle adaya gittik. (We went to the island by ship.)"
  },
  {
    "id": "49",
    "word": "kalabalık",
    "pronunciation": "kah-lah-bah-luhk",
    "meaning": "crowd",
    "part_of_speech": "noun",
    "difficulty": "medium",
    "lesson_no": 7,
    "when_to_say": "When referring to a group of people.",
    "example": "Pazar yeri çok kalabalıktı. (The marketplace was very crowded.)"
  },
  {
    "id": "50",
    "word": "boş",
    "pronunciation": "bosh",
    "meaning": "empty",
    "part_of_speech": "adjective",
    "difficulty": "easy",
    "lesson_no": 7,
    "when_to_say": "When describing something that is empty.",
    "example": "Bardak boş. (The glass is empty.)"
  },
  {
    "id": "51",
    "word": "dolap",
    "pronunciation": "doh-lahp",
    "meaning": "cupboard",
    "part_of_speech": "noun",
    "difficulty": "easy",
    "lesson_no": 7,
    "when_to_say": "When referring to a storage unit.",
    "example": "Dolapta süt var mı? (Is there milk in the cupboard?)"
  },
  {
    "id": "52",
    "word": "kütüphane",
    "pronunciation": "koo-too-pah-neh",
    "meaning": "library",
    "part_of_speech": "noun",
    "difficulty": "easy",
    "lesson_no": 7,
    "when_to_say": "When referring to a place where books are kept.",
    "example": "Kütüphanede ders çalışıyorum. (I am studying at the library.)"
  },
  {
    "id": "53",
    "word": "sokak",
    "pronunciation": "soh-kahk",
    "meaning": "street",
    "part_of_speech": "noun",
    "difficulty": "easy",
    "lesson_no": 8,
    "when_to_say": "When referring to a road or street.",
    "example": "Sokakta çocuklar oynuyor. (Children are playing on the street.)"
  },
  {
    "id": "54",
    "word": "yol",
    "pronunciation": "yohl",
    "meaning": "road",
    "part_of_speech": "noun",
    "difficulty": "easy",
    "lesson_no": 8,
    "when_to_say": "When referring to a road or path.",
    "example": "Yol çok uzundu. (The road was very long.)"
  },
  {
    "id": "55",
    "word": "park",
    "pronunciation": "pahrk",
    "meaning": "park",
    "part_of_speech": "noun",
    "difficulty": "easy",
    "lesson_no": 8,
    "when_to_say": "When referring to a public park.",
    "example": "Parkta yürüyüş yaptık. (We took a walk in the park.)"
  },
  {
    "id": "56",
    "word": "okul",
    "pronunciation": "oh-kool",
    "meaning": "school",
    "part_of_speech": "noun",
    "difficulty": "easy",
    "lesson_no": 8,
    "when_to_say": "When referring to an educational institution.",
    "example": "Okul sabah sekizde başlıyor. (School starts at 8 AM.)"
  },
  {
    "id": "57",
    "word": "üniversite",
    "pronunciation": "oo-nee-vehr-see-teh",
    "meaning": "university",
    "part_of_speech": "noun",
    "difficulty": "medium",
    "lesson_no": 8,
    "when_to_say": "When referring to a university.",
    "example": "Üniversite sınavına hazırlanıyorum. (I am preparing for the university exam.)"
  },
  {
    "id": "58",
    "word": "hava",
    "pronunciation": "hah-vah",
    "meaning": "weather",
    "part_of_speech": "noun",
    "difficulty": "easy",
    "lesson_no": 9,
    "when_to_say": "When discussing the weather.",
    "example": "Hava bugün çok güzel. (The weather is very nice today.)"
  },
  {
    "id": "59",
    "word": "güneş",
    "pronunciation": "goo-nehsh",
    "meaning": "sun",
    "part_of_speech": "noun",
    "difficulty": "easy",
    "lesson_no": 9,
    "when_to_say": "When referring to the sun.",
    "example": "Güneş doğuyor. (The sun is rising.)"
  },
  {
    "id": "60",
    "word": "ay",
    "pronunciation": "eye",
    "meaning": "moon",
    "part_of_speech": "noun",
    "difficulty": "easy",
    "lesson_no": 9,
    "when_to_say": "When referring to the moon.",
    "example": "Ay bu gece çok parlak. (The moon is very bright tonight.)"
  },

  {
    "id": "61",
    "word": "yıldız",
    "pronunciation": "yuhl-duhz",
    "meaning": "star",
    "part_of_speech": "noun",
    "difficulty": "easy",
    "lesson_no": 9,
    "when_to_say": "When referring to stars in the sky.",
    "example": "Gece gökyüzünde yıldızlar çok güzel. (The stars are beautiful in the night sky.)"
  },
  {
    "id": "62",
    "word": "bulut",
    "pronunciation": "boo-loot",
    "meaning": "cloud",
    "part_of_speech": "noun",
    "difficulty": "easy",
    "lesson_no": 9,
    "when_to_say": "When referring to clouds.",
    "example": "Gökyüzü bulutlu. (The sky is cloudy.)"
  },
  {
    "id": "63",
    "word": "yağmur",
    "pronunciation": "yah-moor",
    "meaning": "rain",
    "part_of_speech": "noun",
    "difficulty": "easy",
    "lesson_no": 9,
    "when_to_say": "When referring to rain.",
    "example": "Yağmur yağıyor. (It is raining.)"
  },
  {
    "id": "64",
    "word": "kar",
    "pronunciation": "kahr",
    "meaning": "snow",
    "part_of_speech": "noun",
    "difficulty": "easy",
    "lesson_no": 9,
    "when_to_say": "When referring to snow.",
    "example": "Dağlarda kar var. (There is snow on the mountains.)"
  },
  {
    "id": "65",
    "word": "rüzgar",
    "pronunciation": "roo-zeh-gahr",
    "meaning": "wind",
    "part_of_speech": "noun",
    "difficulty": "easy",
    "lesson_no": 9,
    "when_to_say": "When referring to wind.",
    "example": "Bugün çok rüzgarlı. (It is very windy today.)"
  },
  {
    "id": "66",
    "word": "dağ",
    "pronunciation": "dah",
    "meaning": "mountain",
    "part_of_speech": "noun",
    "difficulty": "easy",
    "lesson_no": 10,
    "when_to_say": "When referring to a mountain.",
    "example": "Dağa tırmanıyoruz. (We are climbing the mountain.)"
  },
  {
    "id": "67",
    "word": "deniz",
    "pronunciation": "deh-neez",
    "meaning": "sea",
    "part_of_speech": "noun",
    "difficulty": "easy",
    "lesson_no": 10,
    "when_to_say": "When referring to the sea.",
    "example": "Denizde yüzmeyi seviyorum. (I love swimming in the sea.)"
  },
  {
    "id": "68",
    "word": "nehir",
    "pronunciation": "neh-heer",
    "meaning": "river",
    "part_of_speech": "noun",
    "difficulty": "easy",
    "lesson_no": 10,
    "when_to_say": "When referring to a river.",
    "example": "Nehir boyunca yürüdük. (We walked along the river.)"
  },
  {
    "id": "69",
    "word": "orman",
    "pronunciation": "or-mahn",
    "meaning": "forest",
    "part_of_speech": "noun",
    "difficulty": "medium",
    "lesson_no": 10,
    "when_to_say": "When referring to a forest.",
    "example": "Ormanda kamp yaptık. (We camped in the forest.)"
  },
  {
    "id": "70",
    "word": "çiçek",
    "pronunciation": "chee-chehk",
    "meaning": "flower",
    "part_of_speech": "noun",
    "difficulty": "easy",
    "lesson_no": 10,
    "when_to_say": "When referring to flowers.",
    "example": "Bahçede çiçekler açmış. (Flowers have bloomed in the garden.)"
  },
  {
    "id": "71",
    "word": "ağaç",
    "pronunciation": "ah-uhch",
    "meaning": "tree",
    "part_of_speech": "noun",
    "difficulty": "easy",
    "lesson_no": 10,
    "when_to_say": "When referring to trees.",
    "example": "Ağaçlar gölgelik yapar. (Trees provide shade.)"
  },
  {
    "id": "72",
    "word": "meyve",
    "pronunciation": "mey-veh",
    "meaning": "fruit",
    "part_of_speech": "noun",
    "difficulty": "easy",
    "lesson_no": 6,
    "when_to_say": "When referring to fruits.",
    "example": "Meyve salatası yaptım. (I made a fruit salad.)"
  },
  {
    "id": "73",
    "word": "sebze",
    "pronunciation": "seb-zeh",
    "meaning": "vegetable",
    "part_of_speech": "noun",
    "difficulty": "easy",
    "lesson_no": 6,
    "when_to_say": "When referring to vegetables.",
    "example": "Sebzeleri doğrayabilir misin? (Can you chop the vegetables?)"
  },
  {
    "id": "74",
    "word": "elma",
    "pronunciation": "ehl-mah",
    "meaning": "apple",
    "part_of_speech": "noun",
    "difficulty": "easy",
    "lesson_no": 6,
    "when_to_say": "When referring to apples.",
    "example": "Elma yemek sağlıklıdır. (Eating apples is healthy.)"
  },
  {
    "id": "75",
    "word": "muz",
    "pronunciation": "mooz",
    "meaning": "banana",
    "part_of_speech": "noun",
    "difficulty": "easy",
    "lesson_no": 6,
    "when_to_say": "When referring to bananas.",
    "example": "Kahvaltıda muz yedim. (I ate a banana for breakfast.)"
  },
  {
    "id": "76",
    "word": "çilek",
    "pronunciation": "chee-lehk",
    "meaning": "strawberry",
    "part_of_speech": "noun",
    "difficulty": "easy",
    "lesson_no": 6,
    "when_to_say": "When referring to strawberries.",
    "example": "Çilek reçeli yaptım. (I made strawberry jam.)"
  },
  {
    "id": "77",
    "word": "domates",
    "pronunciation": "doh-mah-tehs",
    "meaning": "tomato",
    "part_of_speech": "noun",
    "difficulty": "easy",
    "lesson_no": 6,
    "when_to_say": "When referring to tomatoes.",
    "example": "Salataya domates ekledim. (I added tomatoes to the salad.)"
  },
  {
    "id": "78",
    "word": "patates",
    "pronunciation": "pah-tah-tehs",
    "meaning": "potato",
    "part_of_speech": "noun",
    "difficulty": "easy",
    "lesson_no": 6,
    "when_to_say": "When referring to potatoes.",
    "example": "Patates kızartması yaptık. (We made french fries.)"
  },
  {
    "id": "79",
    "word": "havuç",
    "pronunciation": "hah-vooch",
    "meaning": "carrot",
    "part_of_speech": "noun",
    "difficulty": "easy",
    "lesson_no": 6,
    "when_to_say": "When referring to carrots.",
    "example": "Havuç çorbası yapmayı denedim. (I tried making carrot soup.)"
  },
  {
    "id": "80",
    "word": "soğan",
    "pronunciation": "soh-ahn",
    "meaning": "onion",
    "part_of_speech": "noun",
    "difficulty": "easy",
    "lesson_no": 6,
    "when_to_say": "When referring to onions.",
    "example": "Soğan doğramayı öğreniyorum. (I am learning to chop onions.)"
  },

  {
    "id": "81",
    "word": "sarımsak",
    "pronunciation": "sah-rum-sahk",
    "meaning": "garlic",
    "part_of_speech": "noun",
    "difficulty": "easy",
    "lesson_no": 6,
    "when_to_say": "When referring to garlic.",
    "example": "Sarımsak yemeklere lezzet katar. (Garlic adds flavor to dishes.)"
  },
  {
    "id": "82",
    "word": "ekmek",
    "pronunciation": "ehk-mehk",
    "meaning": "bread",
    "part_of_speech": "noun",
    "difficulty": "easy",
    "lesson_no": 6,
    "when_to_say": "When referring to bread.",
    "example": "Sabah kahvaltısında ekmek yedim. (I ate bread for breakfast.)"
  },
  {
    "id": "83",
    "word": "peynir",
    "pronunciation": "pay-neer",
    "meaning": "cheese",
    "part_of_speech": "noun",
    "difficulty": "easy",
    "lesson_no": 6,
    "when_to_say": "When referring to cheese.",
    "example": "Kahvaltıda peynir çok seviyorum. (I love cheese for breakfast.)"
  },
  {
    "id": "84",
    "word": "süt",
    "pronunciation": "süt",
    "meaning": "milk",
    "part_of_speech": "noun",
    "difficulty": "easy",
    "lesson_no": 6,
    "when_to_say": "When referring to milk.",
    "example": "Süt kahvaltının önemli bir parçasıdır. (Milk is an important part of breakfast.)"
  },
  {
    "id": "85",
    "word": "yoğurt",
    "pronunciation": "yo-oort",
    "meaning": "yogurt",
    "part_of_speech": "noun",
    "difficulty": "easy",
    "lesson_no": 6,
    "when_to_say": "When referring to yogurt.",
    "example": "Yoğurt sağlıklı bir yiyecektir. (Yogurt is a healthy food.)"
  },
  {
    "id": "86",
    "word": "bal",
    "pronunciation": "bahl",
    "meaning": "honey",
    "part_of_speech": "noun",
    "difficulty": "easy",
    "lesson_no": 6,
    "when_to_say": "When referring to honey.",
    "example": "Bal tatlı ve doğal bir besindir. (Honey is a sweet and natural food.)"
  },
  {
    "id": "87",
    "word": "yumurta",
    "pronunciation": "yoo-moor-tah",
    "meaning": "egg",
    "part_of_speech": "noun",
    "difficulty": "easy",
    "lesson_no": 6,
    "when_to_say": "When referring to eggs.",
    "example": "Sabah kahvaltısında yumurta yiyorum. (I eat eggs for breakfast.)"
  },
  {
    "id": "88",
    "word": "et",
    "pronunciation": "eht",
    "meaning": "meat",
    "part_of_speech": "noun",
    "difficulty": "easy",
    "lesson_no": 6,
    "when_to_say": "When referring to meat.",
    "example": "Et yemeklerinin tadı harika. (Meat dishes taste amazing.)"
  },
  {
    "id": "89",
    "word": "tavuk",
    "pronunciation": "tah-vook",
    "meaning": "chicken",
    "part_of_speech": "noun",
    "difficulty": "easy",
    "lesson_no": 6,
    "when_to_say": "When referring to chicken.",
    "example": "Bu akşam tavuk pişireceğim. (I will cook chicken tonight.)"
  },
  {
    "id": "90",
    "word": "balık",
    "pronunciation": "bah-luhk",
    "meaning": "fish",
    "part_of_speech": "noun",
    "difficulty": "easy",
    "lesson_no": 6,
    "when_to_say": "When referring to fish.",
    "example": "Balık sağlıklı bir yiyecektir. (Fish is a healthy food.)"
  },
  {
    "id": "91",
    "word": "çorba",
    "pronunciation": "chor-bah",
    "meaning": "soup",
    "part_of_speech": "noun",
    "difficulty": "easy",
    "lesson_no": 7,
    "when_to_say": "When referring to soup.",
    "example": "Kışın çorba içmeyi seviyorum. (I love drinking soup in winter.)"
  },
  {
    "id": "92",
    "word": "pilav",
    "pronunciation": "pee-lahv",
    "meaning": "rice",
    "part_of_speech": "noun",
    "difficulty": "easy",
    "lesson_no": 7,
    "when_to_say": "When referring to cooked rice.",
    "example": "Pilav yapmayı öğreniyorum. (I am learning to make rice.)"
  },
  {
    "id": "93",
    "word": "makarna",
    "pronunciation": "mah-kar-nah",
    "meaning": "pasta",
    "part_of_speech": "noun",
    "difficulty": "easy",
    "lesson_no": 7,
    "when_to_say": "When referring to pasta.",
    "example": "Makarna çok lezzetliydi. (The pasta was very delicious.)"
  },
  {
    "id": "94",
    "word": "salata",
    "pronunciation": "sah-lah-tah",
    "meaning": "salad",
    "part_of_speech": "noun",
    "difficulty": "easy",
    "lesson_no": 7,
    "when_to_say": "When referring to salad.",
    "example": "Salatayı limonla severim. (I like salad with lemon.)"
  },
  {
    "id": "95",
    "word": "şeker",
    "pronunciation": "sheh-kehr",
    "meaning": "sugar",
    "part_of_speech": "noun",
    "difficulty": "easy",
    "lesson_no": 7,
    "when_to_say": "When referring to sugar.",
    "example": "Çaya biraz şeker ekledim. (I added some sugar to the tea.)"
  },
  {
    "id": "96",
    "word": "tuz",
    "pronunciation": "tooz",
    "meaning": "salt",
    "part_of_speech": "noun",
    "difficulty": "easy",
    "lesson_no": 7,
    "when_to_say": "When referring to salt.",
    "example": "Yemeğe tuz koymayı unuttum. (I forgot to add salt to the food.)"
  },
  {
    "id": "97",
    "word": "biber",
    "pronunciation": "bee-behr",
    "meaning": "pepper",
    "part_of_speech": "noun",
    "difficulty": "easy",
    "lesson_no": 7,
    "when_to_say": "When referring to pepper.",
    "example": "Biberler çok acıydı. (The peppers were very spicy.)"
  },
  {
    "id": "98",
    "word": "yağ",
    "pronunciation": "yah",
    "meaning": "oil",
    "part_of_speech": "noun",
    "difficulty": "easy",
    "lesson_no": 7,
    "when_to_say": "When referring to oil.",
    "example": "Yemek pişirirken biraz yağ ekledim. (I added some oil while cooking.)"
  },
  {
    "id": "99",
    "word": "kahve",
    "pronunciation": "kah-veh",
    "meaning": "coffee",
    "part_of_speech": "noun",
    "difficulty": "easy",
    "lesson_no": 7,
    "when_to_say": "When referring to coffee.",
    "example": "Sabah kahvesiz uyanamam. (I can't wake up without coffee in the morning.)"
  },
  {
    "id": "100",
    "word": "çay",
    "pronunciation": "chai",
    "meaning": "tea",
    "part_of_speech": "noun",
    "difficulty": "easy",
    "lesson_no": 7,
    "when_to_say": "When referring to tea.",
    "example": "Türk çayı çok meşhurdur. (Turkish tea is very famous.)"
  },
  {
    "id": "101",
    "word": "su",
    "pronunciation": "soo",
    "meaning": "water",
    "part_of_speech": "noun",
    "difficulty": "easy",
    "lesson_no": 7,
    "when_to_say": "When referring to water.",
    "example": "Bir bardak su rica ederim. (I would like a glass of water.)"
  },

  {
    "id": "102",
    "word": "meyve suyu",
    "pronunciation": "mey-veh soo-yoo",
    "meaning": "juice",
    "part_of_speech": "noun",
    "difficulty": "easy",
    "lesson_no": 7,
    "when_to_say": "When referring to fruit juice.",
    "example": "Kahvaltıda meyve suyu içtim. (I drank juice for breakfast.)"
  },
  {
    "id": "103",
    "word": "limonata",
    "pronunciation": "lee-moh-nah-tah",
    "meaning": "lemonade",
    "part_of_speech": "noun",
    "difficulty": "easy",
    "lesson_no": 7,
    "when_to_say": "When referring to lemonade.",
    "example": "Sıcak günlerde limonata içerim. (I drink lemonade on hot days.)"
  },
  {
    "id": "104",
    "word": "gazoz",
    "pronunciation": "gah-zoz",
    "meaning": "soda",
    "part_of_speech": "noun",
    "difficulty": "easy",
    "lesson_no": 7,
    "when_to_say": "When referring to soda.",
    "example": "Gazozu çok seviyorum. (I love soda.)"
  },
  {
    "id": "105",
    "word": "dondurma",
    "pronunciation": "dohn-door-mah",
    "meaning": "ice cream",
    "part_of_speech": "noun",
    "difficulty": "easy",
    "lesson_no": 8,
    "when_to_say": "When referring to ice cream.",
    "example": "Dondurma sıcak yaz günlerinde harikadır. (Ice cream is great on hot summer days.)"
  },
  {
    "id": "106",
    "word": "tatlı",
    "pronunciation": "taht-luh",
    "meaning": "dessert",
    "part_of_speech": "noun",
    "difficulty": "easy",
    "lesson_no": 8,
    "when_to_say": "When referring to sweet dishes or desserts.",
    "example": "Tatlı yemekten sonra servis edilir. (Dessert is served after a meal.)"
  },
  {
    "id": "107",
    "word": "çikolata",
    "pronunciation": "chee-koh-lah-tah",
    "meaning": "chocolate",
    "part_of_speech": "noun",
    "difficulty": "easy",
    "lesson_no": 8,
    "when_to_say": "When referring to chocolate.",
    "example": "Çikolata çok lezzetli bir atıştırmalıktır. (Chocolate is a very delicious snack.)"
  },
  {
    "id": "108",
    "word": "pasta",
    "pronunciation": "pahs-tah",
    "meaning": "cake",
    "part_of_speech": "noun",
    "difficulty": "easy",
    "lesson_no": 8,
    "when_to_say": "When referring to cake.",
    "example": "Doğum gününde pasta kestik. (We cut a cake for the birthday.)"
  },
  {
    "id": "109",
    "word": "kurabiye",
    "pronunciation": "koo-rah-bee-yeh",
    "meaning": "cookie",
    "part_of_speech": "noun",
    "difficulty": "easy",
    "lesson_no": 8,
    "when_to_say": "When referring to cookies.",
    "example": "Kurabiye çayın yanında harikadır. (Cookies are great with tea.)"
  },
  {
    "id": "110",
    "word": "aile",
    "pronunciation": "ah-ee-leh",
    "meaning": "family",
    "part_of_speech": "noun",
    "difficulty": "easy",
    "lesson_no": 8,
    "when_to_say": "When talking about family members collectively.",
    "example": "Aile, hayattaki en önemli şeydir. (Family is the most important thing in life.)"
  },
  {
    "id": "111",
    "word": "anne",
    "pronunciation": "ahn-neh",
    "meaning": "mother",
    "part_of_speech": "noun",
    "difficulty": "easy",
    "lesson_no": 8,
    "when_to_say": "When referring to your mother.",
    "example": "Anne yemek yapıyor. (Mom is cooking.)"
  },
  {
    "id": "112",
    "word": "baba",
    "pronunciation": "bah-bah",
    "meaning": "father",
    "part_of_speech": "noun",
    "difficulty": "easy",
    "lesson_no": 8,
    "when_to_say": "When referring to your father.",
    "example": "Babam işe gitti. (My father went to work.)"
  },
  {
    "id": "113",
    "word": "kardeş",
    "pronunciation": "kahr-desh",
    "meaning": "sibling",
    "part_of_speech": "noun",
    "difficulty": "easy",
    "lesson_no": 8,
    "when_to_say": "When referring to your brother or sister.",
    "example": "Kardeşim okulda. (My sibling is at school.)"
  },
  {
    "id": "114",
    "word": "abi",
    "pronunciation": "ah-bee",
    "meaning": "older brother",
    "part_of_speech": "noun",
    "difficulty": "easy",
    "lesson_no": 8,
    "when_to_say": "When referring to your older brother.",
    "example": "Abim kitap okuyor. (My older brother is reading a book.)"
  },
  {
    "id": "115",
    "word": "abla",
    "pronunciation": "ah-blah",
    "meaning": "older sister",
    "part_of_speech": "noun",
    "difficulty": "easy",
    "lesson_no": 8,
    "when_to_say": "When referring to your older sister.",
    "example": "Ablam pasta yapıyor. (My older sister is making a cake.)"
  },
  {
    "id": "116",
    "word": "çocuk",
    "pronunciation": "cho-jook",
    "meaning": "child",
    "part_of_speech": "noun",
    "difficulty": "easy",
    "lesson_no": 8,
    "when_to_say": "When referring to a young person.",
    "example": "Çocuklar parkta oynuyor. (The children are playing in the park.)"
  },
  {
    "id": "117",
    "word": "bebek",
    "pronunciation": "beh-behk",
    "meaning": "baby",
    "part_of_speech": "noun",
    "difficulty": "easy",
    "lesson_no": 8,
    "when_to_say": "When referring to an infant.",
    "example": "Bebek çok sevimli. (The baby is very cute.)"
  },
  {
    "id": "118",
    "word": "eş",
    "pronunciation": "ehsh",
    "meaning": "spouse",
    "part_of_speech": "noun",
    "difficulty": "easy",
    "lesson_no": 8,
    "when_to_say": "When referring to your husband or wife.",
    "example": "Eşimle birlikte tatile gidiyoruz. (We are going on vacation with my spouse.)"
  },
  {
    "id": "119",
    "word": "arkadaş",
    "pronunciation": "ahr-kah-dahsh",
    "meaning": "friend",
    "part_of_speech": "noun",
    "difficulty": "easy",
    "lesson_no": 8,
    "when_to_say": "When referring to a companion.",
    "example": "Arkadaşım beni ziyarete geldi. (My friend came to visit me.)"
  },
  {
    "id": "120",
    "word": "komşu",
    "pronunciation": "kohm-shoo",
    "meaning": "neighbor",
    "part_of_speech": "noun",
    "difficulty": "easy",
    "lesson_no": 9,
    "when_to_say": "When referring to a neighbor.",
    "example": "Komşularımız çok nazik. (Our neighbors are very kind.)"
  },

  {
    "Id": "121",
    "word": "Humanitarian",
    "pronunciation": "hyoo-muh-NAIR-ee-uhn",
    "meaning": "concerned with or seeking to promote human welfare",
    "part_of_speech": "adjective",
    "difficulty": "medium",
    "Lesson_no": 3,
    "when_to_say": "When referring to actions or policies intended to benefit people in need.",
    "example": "The humanitarian aid was essential after the flood disaster."
  },
  {
    "Id": "122",
    "word": "Relief",
    "pronunciation": "ri-LEEF",
    "meaning": "assistance provided to help people in difficult situations",
    "part_of_speech": "noun",
    "difficulty": "easy",
    "Lesson_no": 2,
    "when_to_say": "When talking about help provided to those in distress or need.",
    "example": "The relief workers provided food and water to the victims."
  },
  {
    "Id": "123",
    "word": "Philanthropy",
    "pronunciation": "fi-LAN-thruh-pee",
    "meaning": "the desire to promote the welfare of others, expressed especially by the donation of money to good causes",
    "part_of_speech": "noun",
    "difficulty": "medium",
    "Lesson_no": 4,
    "when_to_say": "When referring to charitable acts or donations made for the betterment of society.",
    "example": "Her philanthropy helped build schools for underprivileged children."
  },
  {
    "Id": "124",
    "word": "Compassion",
    "pronunciation": "kuhm-PASH-uhn",
    "meaning": "sympathetic pity and concern for the sufferings or misfortunes of others",
    "part_of_speech": "noun",
    "difficulty": "easy",
    "Lesson_no": 1,
    "when_to_say": "When expressing a feeling of empathy or kindness towards someone in need.",
    "example": "He showed great compassion by donating to the flood victims."
  },
  {
    "Id": "125",
    "word": "Solidarity",
    "pronunciation": "suh-LID-uh-ree-tee",
    "meaning": "unity or agreement of feeling or action, especially among individuals with a common interest",
    "part_of_speech": "noun",
    "difficulty": "medium",
    "Lesson_no": 5,
    "when_to_say": "When referring to mutual support or unity in a cause.",
    "example": "The community showed solidarity by contributing to the relief fund."
  },
  {
    "Id": "126",
    "word": "Resilience",
    "pronunciation": "ri-ZIL-yuhns",
    "meaning": "the capacity to recover quickly from difficulties",
    "part_of_speech": "noun",
    "difficulty": "medium",
    "Lesson_no": 6,
    "when_to_say": "When talking about the ability to overcome adversity or bounce back from challenges.",
    "example": "The resilience of the people after the disaster was inspiring."
  },
  {
    "Id": "127",
    "word": "Empathy",
    "pronunciation": "EM-puh-thee",
    "meaning": "the ability to understand and share the feelings of another",
    "part_of_speech": "noun",
    "difficulty": "easy",
    "Lesson_no": 7,
    "when_to_say": "When expressing understanding and sharing someone else's emotional experience.",
    "example": "She showed great empathy towards the earthquake survivors."
  },
  {
    "Id": "128",
    "word": "Volunteer",
    "pronunciation": "vol-uhn-TEER",
    "meaning": "a person who freely offers to take part in an enterprise or undertake a task",
    "part_of_speech": "noun",
    "difficulty": "easy",
    "Lesson_no": 8,
    "when_to_say": "When referring to someone offering help or services without expecting payment.",
    "example": "The volunteers worked tirelessly to distribute food and aid."
  },
  {
    "Id": "129",
    "word": "Charity",
    "pronunciation": "CHAIR-ih-tee",
    "meaning": "the voluntary giving of help, typically in the form of money, to those in need",
    "part_of_speech": "noun",
    "difficulty": "easy",
    "Lesson_no": 2,
    "when_to_say": "When talking about the act of giving to those less fortunate.",
    "example": "The charity event raised a significant amount for the flood victims."
  },
  {
    "Id": "130",
    "word": "Contribution",
    "pronunciation": "kon-truh-BYOO-shun",
    "meaning": "a gift or payment to a common fund or cause",
    "part_of_speech": "noun",
    "difficulty": "medium",
    "Lesson_no": 6,
    "when_to_say": "When talking about donating or giving towards a cause.",
    "example": "His contribution to the flood relief fund was greatly appreciated."
  },

  {
    "Id": "131",
    "word": "Aid",
    "pronunciation": "ayd",
    "meaning": "help, typically of a practical nature, provided to those in need",
    "part_of_speech": "noun",
    "difficulty": "easy",
    "Lesson_no": 1,
    "when_to_say": "When referring to assistance provided to people in difficult situations.",
    "example": "The government sent aid to the flood victims immediately."
  },
  {
    "Id": "132",
    "word": "Campaign",
    "pronunciation": "kam-PAIN",
    "meaning": "a series of organized activities or actions aimed at achieving a specific goal",
    "part_of_speech": "noun",
    "difficulty": "medium",
    "Lesson_no": 3,
    "when_to_say": "When discussing a series of actions taken to promote or achieve a particular objective.",
    "example": "The charity launched a campaign to raise funds for the disaster victims."
  },
  {
    "Id": "133",
    "word": "Donation",
    "pronunciation": "doh-NAY-shun",
    "meaning": "a gift or contribution made to a person, organization, or cause",
    "part_of_speech": "noun",
    "difficulty": "easy",
    "Lesson_no": 2,
    "when_to_say": "When referring to something given to help a cause or someone in need.",
    "example": "She made a generous donation to the relief fund."
  },
  {
    "Id": "134",
    "word": "Disaster",
    "pronunciation": "di-ZAS-tur",
    "meaning": "a sudden event, such as an accident or a natural catastrophe, that causes great damage or loss of life",
    "part_of_speech": "noun",
    "difficulty": "medium",
    "Lesson_no": 5,
    "when_to_say": "When referring to a sudden and catastrophic event, typically natural.",
    "example": "The hurricane was a disaster that left thousands homeless."
  },
  {
    "Id": "135",
    "word": "Recovery",
    "pronunciation": "ri-KUV-uh-ree",
    "meaning": "the process of returning to a normal state of health, mind, or strength",
    "part_of_speech": "noun",
    "difficulty": "medium",
    "Lesson_no": 7,
    "when_to_say": "When referring to the process of regaining strength or normalcy after a crisis.",
    "example": "The city began its recovery after the earthquake, with rebuilding efforts underway."
  },
  {
    "Id": "136",
    "word": "Hope",
    "pronunciation": "hohp",
    "meaning": "a feeling of expectation and desire for a certain thing to happen",
    "part_of_speech": "noun",
    "difficulty": "easy",
    "Lesson_no": 1,
    "when_to_say": "When expressing a positive expectation for the future.",
    "example": "The community's hope was restored after the relief arrived."
  },
  {
    "Id": "137",
    "word": "Urgent",
    "pronunciation": "UR-juhnt",
    "meaning": "requiring immediate action or attention",
    "part_of_speech": "adjective",
    "difficulty": "medium",
    "Lesson_no": 4,
    "when_to_say": "When something needs immediate action or attention.",
    "example": "The relief team responded to the urgent needs of the flood victims."
  },
  {
    "Id": "138",
    "word": "Gratitude",
    "pronunciation": "GRAT-i-tood",
    "meaning": "the quality of being thankful; readiness to show appreciation for and to return kindness",
    "part_of_speech": "noun",
    "difficulty": "medium",
    "Lesson_no": 3,
    "when_to_say": "When expressing thanks or appreciation for something or someone.",
    "example": "The survivors expressed their gratitude for the aid they received."
  },
  {
    "Id": "139",
    "word": "Generosity",
    "pronunciation": "jen-uh-ROS-i-tee",
    "meaning": "the quality of being kind and generous",
    "part_of_speech": "noun",
    "difficulty": "medium",
    "Lesson_no": 5,
    "when_to_say": "When talking about the act of being kind and giving to others.",
    "example": "His generosity knew no bounds, and he donated all his savings to the relief effort."
  },
  {
    "Id": "140",
    "word": "Support",
    "pronunciation": "su-PORT",
    "meaning": "to give assistance or help to someone or something",
    "part_of_speech": "verb",
    "difficulty": "easy",
    "Lesson_no": 2,
    "when_to_say": "When helping or assisting someone, typically in times of need.",
    "example": "The organization supported the victims of the disaster with food and supplies."
  },
  {
    "Id": "141",
    "word": "Donate",
    "pronunciation": "doh-NAYT",
    "meaning": "to give something, especially money, to a charity or cause",
    "part_of_speech": "verb",
    "difficulty": "easy",
    "Lesson_no": 6,
    "when_to_say": "When giving or contributing to a cause or charity.",
    "example": "She decided to donate a portion of her salary to the disaster relief fund."
  },
  {
    "Id": "142",
    "word": "Fundraiser",
    "pronunciation": "FUN-dray-zur",
    "meaning": "an event or activity organized to raise money for a particular cause",
    "part_of_speech": "noun",
    "difficulty": "medium",
    "Lesson_no": 8,
    "when_to_say": "When referring to events or activities designed to raise money for a specific cause.",
    "example": "The school organized a fundraiser to collect donations for the disaster victims."
  },
  {
    "Id": "143",
    "word": "Volunteerism",
    "pronunciation": "vol-un-TEER-izm",
    "meaning": "the use or involvement of volunteer labor, typically for charitable causes",
    "part_of_speech": "noun",
    "difficulty": "medium",
    "Lesson_no": 4,
    "when_to_say": "When referring to the act of volunteering or offering services without compensation.",
    "example": "Her volunteerism during the relief effort inspired others to contribute."
  },
  {
    "Id": "144",
    "word": "Collaboration",
    "pronunciation": "kuh-lab-uh-REY-shun",
    "meaning": "the action of working with someone to produce or create something",
    "part_of_speech": "noun",
    "difficulty": "medium",
    "Lesson_no": 7,
    "when_to_say": "When working together with others towards a common goal.",
    "example": "The collaboration between various NGOs helped speed up the relief process."
  },
  {
    "Id": "145",
    "word": "Solidarity",
    "pronunciation": "sol-i-DAR-i-tee",
    "meaning": "unity or agreement of feeling or action, especially among individuals with a common interest",
    "part_of_speech": "noun",
    "difficulty": "medium",
    "Lesson_no": 9,
    "when_to_say": "When referring to mutual support or unity in a cause.",
    "example": "The international solidarity with the disaster-stricken areas was overwhelming."
  },
  {
    "Id": "146",
    "word": "Rebuild",
    "pronunciation": "ree-BILD",
    "meaning": "to build something again after it has been damaged or destroyed",
    "part_of_speech": "verb",
    "difficulty": "medium",
    "Lesson_no": 6,
    "when_to_say": "When discussing the act of constructing or repairing something after damage.",
    "example": "The town began to rebuild after the devastating earthquake."
  },
  {
    "Id": "147",
    "word": "Relocate",
    "pronunciation": "ree-LOH-kayt",
    "meaning": "to move to a new place, typically for safety or work",
    "part_of_speech": "verb",
    "difficulty": "medium",
    "Lesson_no": 5,
    "when_to_say": "When referring to the act of moving to a new location, often due to necessity.",
    "example": "The residents had to relocate due to the rising floodwaters."
  },
  {
    "Id": "148",
    "word": "Sustain",
    "pronunciation": "suh-STAYN",
    "meaning": "to support, nourish, or maintain over time",
    "part_of_speech": "verb",
    "difficulty": "medium",
    "Lesson_no": 4,
    "when_to_say": "When talking about keeping something going or maintaining a condition.",
    "example": "The funds will help sustain the relief efforts for the long term."
  },
  {
    "Id": "149",
    "word": "Protection",
    "pronunciation": "pro-TEK-shun",
    "meaning": "the action of keeping someone or something safe from harm or danger",
    "part_of_speech": "noun",
    "difficulty": "medium",
    "Lesson_no": 9,
    "when_to_say": "When talking about the act of defending or keeping something safe.",
    "example": "The humanitarian organizations provided protection to those displaced by the disaster."
  },
  {
    "Id": "150",
    "word": "Hopeful",
    "pronunciation": "HOHP-fuhl",
    "meaning": "feeling or inspiring optimism about a future event",
    "part_of_speech": "adjective",
    "difficulty": "easy",
    "Lesson_no": 3,
    "when_to_say": "When expressing a positive outlook or belief in future success.",
    "example": "Despite the challenges, the community remained hopeful about the recovery."
  },
  {
    "Id": "151",
    "word": "Survivor",
    "pronunciation": "ser-VYE-vur",
    "meaning": "a person who continues to live after an event or experience that causes others to die or suffer",
    "part_of_speech": "noun",
    "difficulty": "medium",
    "Lesson_no": 8,
    "when_to_say": "When referring to a person who has lived through a difficult or life-threatening event.",
    "example": "The survivors of the earthquake shared their stories of resilience."
  },

  {
    "id": "152",
    "word": "momentous",
    "pronunciation": "muh-MEN-tus",
    "meaning": "of great importance or significance",
    "part_of_speech": "adjective",
    "difficulty": "medium",
    "Lesson_no": 5,
    "when_to_say": "when describing events or decisions of great significance",
    "example": "The momentous decision to move abroad changed their lives forever."
  },
  {
    "id": "153",
    "word": "resilient",
    "pronunciation": "ri-ZIL-yent",
    "meaning": "able to recover quickly from difficulties",
    "part_of_speech": "adjective",
    "difficulty": "medium",
    "Lesson_no": 4,
    "when_to_say": "when describing a person or object that bounces back or recovers from a difficult situation",
    "example": "Despite the hardships, she remained resilient and kept moving forward."
  },
  {
    "id": "154",
    "word": "contemplate",
    "pronunciation": "KON-tem-plate",
    "meaning": "to think deeply about something",
    "part_of_speech": "verb",
    "difficulty": "medium",
    "Lesson_no": 6,
    "when_to_say": "when considering or reflecting deeply on a matter",
    "example": "He sat quietly to contemplate the choices he had before him."
  },
  {
    "id": "155",
    "word": "lucid",
    "pronunciation": "LOO-sid",
    "meaning": "expressed clearly; easy to understand",
    "part_of_speech": "adjective",
    "difficulty": "medium",
    "Lesson_no": 4,
    "when_to_say": "when describing clear, understandable speech or writing",
    "example": "The professor’s explanation was so lucid that everyone understood the complex topic."
  },
  {
    "id": "156",
    "word": "benevolent",
    "pronunciation": "buh-NEV-uh-lent",
    "meaning": "well-meaning and kindly",
    "part_of_speech": "adjective",
    "difficulty": "medium",
    "Lesson_no": 3,
    "when_to_say": "when describing someone who is kind and charitable",
    "example": "Her benevolent nature led her to volunteer at the shelter every weekend."
  },
  {
    "id": "157",
    "word": "incisive",
    "pronunciation": "in-SAI-siv",
    "meaning": "clear, sharp, and direct in expression",
    "part_of_speech": "adjective",
    "difficulty": "medium",
    "Lesson_no": 5,
    "when_to_say": "when describing a comment or action that cuts through confusion",
    "example": "His incisive questions during the meeting helped clarify the issue immediately."
  },
  {
    "id": "158",
    "word": "elusive",
    "pronunciation": "ih-LOO-siv",
    "meaning": "difficult to find, catch, or achieve",
    "part_of_speech": "adjective",
    "difficulty": "medium",
    "Lesson_no": 4,
    "when_to_say": "when describing something that is hard to grasp or understand",
    "example": "The solution to the puzzle was so elusive that no one could figure it out."
  },
  {
    "id": "159",
    "word": "meticulous",
    "pronunciation": "mi-TIK-yuh-lus",
    "meaning": "showing great attention to detail; very careful and precise",
    "part_of_speech": "adjective",
    "difficulty": "medium",
    "Lesson_no": 6,
    "when_to_say": "when describing someone who is extremely careful and precise",
    "example": "The artist was meticulous in painting every fine detail of the portrait."
  },
  {
    "id": "160",
    "word": "vehement",
    "pronunciation": "VEE-uh-ment",
    "meaning": "showing strong feeling; forceful, passionate, or intense",
    "part_of_speech": "adjective",
    "difficulty": "medium",
    "Lesson_no": 5,
    "when_to_say": "when expressing strong emotions or opinions",
    "example": "She was vehement in her defense of her beliefs."
  },
  {
    "id": "161",
    "word": "cogent",
    "pronunciation": "KO-jent",
    "meaning": "clear, logical, and convincing",
    "part_of_speech": "adjective",
    "difficulty": "medium",
    "Lesson_no": 6,
    "when_to_say": "when describing an argument or reasoning that is strong and convincing",
    "example": "His cogent argument persuaded everyone to agree with his proposal."
  },
  {
    "id": "162",
    "word": "empirical",
    "pronunciation": "em-PEER-ih-kul",
    "meaning": "based on observation or experience rather than theory",
    "part_of_speech": "adjective",
    "difficulty": "medium",
    "Lesson_no": 7,
    "when_to_say": "when describing something grounded in actual data or experience",
    "example": "The scientific method relies heavily on empirical data to form conclusions."
  },
  {
    "id": "163",
    "word": "precarious",
    "pronunciation": "pri-KAIR-ee-us",
    "meaning": "not securely held or in position; dangerously likely to fall or collapse",
    "part_of_speech": "adjective",
    "difficulty": "medium",
    "Lesson_no": 4,
    "when_to_say": "when describing a situation that is risky or unstable",
    "example": "The climbers found themselves in a precarious position on the mountain."
  },
  {
    "id": "164",
    "word": "concur",
    "pronunciation": "kun-KUR",
    "meaning": "to agree or have the same opinion",
    "part_of_speech": "verb",
    "difficulty": "medium",
    "Lesson_no": 5,
    "when_to_say": "when expressing agreement with someone’s opinion or action",
    "example": "I concur with your idea and believe we should proceed with the plan."
  },
  {
    "id": "165",
    "word": "juxtapose",
    "pronunciation": "JUK-stuh-pohz",
    "meaning": "to place two things side by side to compare or contrast them",
    "part_of_speech": "verb",
    "difficulty": "medium",
    "Lesson_no": 6,
    "when_to_say": "when comparing two different things to highlight their contrasts",
    "example": "The artist juxtaposed dark and light tones in the painting to create a striking contrast."
  },
  {
    "id": "166",
    "word": "arbitrary",
    "pronunciation": "AR-bi-trer-ee",
    "meaning": "based on random choice or personal whim, rather than any reason or system",
    "part_of_speech": "adjective",
    "difficulty": "medium",
    "Lesson_no": 7,
    "when_to_say": "when referring to decisions or actions that are made without logical reason",
    "example": "The manager made an arbitrary decision to change the work schedule without consulting anyone."
  },
  {
    "id": "167",
    "word": "ubiquitous",
    "pronunciation": "yoo-BIK-wi-tus",
    "meaning": "present, appearing, or found everywhere",
    "part_of_speech": "adjective",
    "difficulty": "medium",
    "Lesson_no": 8,
    "when_to_say": "when describing something that is widespread or common",
    "example": "Smartphones have become ubiquitous in modern society."
  },
  {
    "id": "168",
    "word": "ambivalent",
    "pronunciation": "am-BIV-uh-lent",
    "meaning": "having mixed feelings or contradictory ideas about something or someone",
    "part_of_speech": "adjective",
    "difficulty": "medium",
    "Lesson_no": 9,
    "when_to_say": "when describing someone who has conflicting emotions about a decision or situation",
    "example": "He felt ambivalent about accepting the new job offer."
  },
  {
    "id": "169",
    "word": "metamorphosis",
    "pronunciation": "met-uh-MOR-fuh-sis",
    "meaning": "a change of the form or nature of a thing or person into a completely different one",
    "part_of_speech": "noun",
    "difficulty": "medium",
    "Lesson_no": 6,
    "when_to_say": "when describing a complete transformation or change",
    "example": "The caterpillar undergoes a metamorphosis to become a butterfly."
  },
  {
    "id": "170",
    "word": "inundate",
    "pronunciation": "IN-un-dayt",
    "meaning": "to overwhelm with things or people to be dealt with",
    "part_of_speech": "verb",
    "difficulty": "medium",
    "Lesson_no": 7,
    "when_to_say": "when overwhelmed with a large number of things or people",
    "example": "The city was inundated with tourists during the festival."
  },

  {
    "id": "171",
    "word": "cumbersome",
    "pronunciation": "KUM-ber-sum",
    "meaning": "large or heavy and difficult to carry or handle",
    "part_of_speech": "adjective",
    "difficulty": "medium",
    "Lesson_no": 7,
    "when_to_say": "when describing something that is unwieldy or difficult to manage",
    "example": "The old, cumbersome machinery took up a lot of space in the factory."
  },
  {
    "id": "172",
    "word": "convoluted",
    "pronunciation": "CON-vuh-loo-ted",
    "meaning": "extremely complex and difficult to follow",
    "part_of_speech": "adjective",
    "difficulty": "medium",
    "Lesson_no": 8,
    "when_to_say": "when describing something that is complicated or twisted in a way that is hard to understand",
    "example": "The plot of the movie was so convoluted that I had trouble keeping track of the story."
  },
  {
    "id": "173",
    "word": "ameliorate",
    "pronunciation": "uh-MEE-lee-uh-rayt",
    "meaning": "to make something better or more bearable",
    "part_of_speech": "verb",
    "difficulty": "medium",
    "Lesson_no": 6,
    "when_to_say": "when describing an improvement or alleviation of a problem",
    "example": "The new policies were designed to ameliorate the living conditions of the poor."
  },
  {
    "id": "174",
    "word": "mendacious",
    "pronunciation": "men-DAY-shus",
    "meaning": "not telling the truth; lying",
    "part_of_speech": "adjective",
    "difficulty": "medium",
    "Lesson_no": 9,
    "when_to_say": "when describing someone who is deceitful or dishonest",
    "example": "The politician's mendacious statements led to his downfall."
  },
  {
    "id": "175",
    "word": "disparate",
    "pronunciation": "DIS-puh-rit",
    "meaning": "essentially different in kind; not allowing comparison",
    "part_of_speech": "adjective",
    "difficulty": "medium",
    "Lesson_no": 8,
    "when_to_say": "when describing things that are so different that they can't be compared directly",
    "example": "The two cultures were so disparate that they had trouble understanding each other."
  },
  {
    "id": "176",
    "word": "pragmatic",
    "pronunciation": "prag-MAT-ik",
    "meaning": "dealing with things sensibly and realistically",
    "part_of_speech": "adjective",
    "difficulty": "medium",
    "Lesson_no": 5,
    "when_to_say": "when describing someone who is practical and focused on real-world results",
    "example": "His pragmatic approach to problem-solving made him a valuable team member."
  },
  {
    "id": "177",
    "word": "cogitate",
    "pronunciation": "KAH-jih-tayt",
    "meaning": "to think deeply about something",
    "part_of_speech": "verb",
    "difficulty": "medium",
    "Lesson_no": 6,
    "when_to_say": "when describing the act of thinking carefully or considering something in depth",
    "example": "I need time to cogitate on your suggestion before I make a decision."
  },
  {
    "id": "178",
    "word": "effervescent",
    "pronunciation": "ef-er-VES-uhnt",
    "meaning": "bubbling with high spirits; enthusiastic",
    "part_of_speech": "adjective",
    "difficulty": "medium",
    "Lesson_no": 4,
    "when_to_say": "when describing someone who is full of life and energy",
    "example": "Her effervescent personality made her the life of the party."
  },
  {
    "id": "179",
    "word": "fortuitous",
    "pronunciation": "for-TOO-ih-tus",
    "meaning": "happening by chance or accident, often in a lucky way",
    "part_of_speech": "adjective",
    "difficulty": "medium",
    "Lesson_no": 5,
    "when_to_say": "when describing an event or situation that occurs unexpectedly, often with a positive outcome",
    "example": "It was a fortuitous meeting that led to a great business partnership."
  },
  {
    "id": "180",
    "word": "disseminate",
    "pronunciation": "di-SEM-uh-nayt",
    "meaning": "to spread or distribute information widely",
    "part_of_speech": "verb",
    "difficulty": "medium",
    "Lesson_no": 6,
    "when_to_say": "when referring to the act of spreading information or knowledge",
    "example": "The organization works to disseminate information about health and safety."
  },
  {
    "id": "181",
    "word": "abrogate",
    "pronunciation": "AB-roh-gayt",
    "meaning": "to repeal or do away with a law or agreement",
    "part_of_speech": "verb",
    "difficulty": "medium",
    "Lesson_no": 7,
    "when_to_say": "when describing the cancellation or invalidation of a rule or law",
    "example": "The government decided to abrogate the outdated law."
  },
  {
    "id": "182",
    "word": "ephemeral",
    "pronunciation": "ih-FEM-er-ul",
    "meaning": "lasting for a very short time",
    "part_of_speech": "adjective",
    "difficulty": "medium",
    "Lesson_no": 8,
    "when_to_say": "when describing something that is short-lived or fleeting",
    "example": "The beauty of the sunset was ephemeral, disappearing as quickly as it arrived."
  },
  {
    "id": "183",
    "word": "recalcitrant",
    "pronunciation": "ri-KAL-si-trant",
    "meaning": "having a stubborn or uncooperative attitude",
    "part_of_speech": "adjective",
    "difficulty": "medium",
    "Lesson_no": 9,
    "when_to_say": "when describing someone who resists authority or control",
    "example": "The recalcitrant student refused to follow the teacher’s instructions."
  },
  {
    "id": "184",
    "word": "nebulous",
    "pronunciation": "NEB-yuh-lus",
    "meaning": "vague or unclear",
    "part_of_speech": "adjective",
    "difficulty": "medium",
    "Lesson_no": 7,
    "when_to_say": "when describing something that is unclear or difficult to understand",
    "example": "His explanation was so nebulous that no one could understand his point."
  },
  {
    "id": "185",
    "word": "warranted",
    "pronunciation": "WAHR-uhn-tid",
    "meaning": "justified, deserved, or necessary",
    "part_of_speech": "adjective",
    "difficulty": "medium",
    "Lesson_no": 8,
    "when_to_say": "when something is justified or reasonable based on circumstances",
    "example": "The protest was warranted given the unfair treatment they had received."
  },
  {
    "id": "186",
    "word": "equanimity",
    "pronunciation": "ee-kwuh-NIM-ih-tee",
    "meaning": "mental calmness, composure, and evenness of temper, especially in a difficult situation",
    "part_of_speech": "noun",
    "difficulty": "medium",
    "Lesson_no": 9,
    "when_to_say": "when describing someone who remains calm and collected under pressure",
    "example": "She faced the challenges with remarkable equanimity."
  },
  {
    "id": "187",
    "word": "perspicacious",
    "pronunciation": "per-spi-KAY-shus",
    "meaning": "having a ready insight into and understanding of things",
    "part_of_speech": "adjective",
    "difficulty": "medium",
    "Lesson_no": 10,
    "when_to_say": "when describing someone who is highly perceptive or insightful",
    "example": "The perspicacious detective immediately noticed the small but important detail."
  },
  {
    "id": "188",
    "word": "meticulous",
    "pronunciation": "mi-TIK-yuh-lus",
    "meaning": "showing great attention to detail; very careful and precise",
    "part_of_speech": "adjective",
    "difficulty": "medium",
    "Lesson_no": 6,
    "when_to_say": "when describing someone who is extremely careful and precise",
    "example": "The artist was meticulous in painting every fine detail of the portrait."
  },
  {
    "id": "189",
    "word": "indefatigable",
    "pronunciation": "in-di-FAT-i-guh-bul",
    "meaning": "persisting tirelessly",
    "part_of_speech": "adjective",
    "difficulty": "medium",
    "Lesson_no": 8,
    "when_to_say": "when describing someone who never gets tired or gives up",
    "example": "Her indefatigable spirit kept her going through the toughest times."
  },
  {
    "id": "190",
    "word": "exonerate",
    "pronunciation": "ig-ZON-uh-rayt",
    "meaning": "to clear someone of blame or wrongdoing",
    "part_of_speech": "verb",
    "difficulty": "medium",
    "Lesson_no": 7,
    "when_to_say": "when someone is cleared of blame or suspicion",
    "example": "The evidence exonerated the suspect, proving his innocence."
  },
  {
    "id": "191",
    "word": "vociferous",
    "pronunciation": "voh-SIF-er-us",
    "meaning": "expressing opinions loudly and forcefully",
    "part_of_speech": "adjective",
    "difficulty": "medium",
    "Lesson_no": 8,
    "when_to_say": "when describing someone who is loud and outspoken",
    "example": "The vociferous protestors demanded change from the government."
  },
  {
    "id": "192",
    "word": "solicitous",
    "pronunciation": "suh-LIS-ih-tus",
    "meaning": "showing concern or care for someone's well-being",
    "part_of_speech": "adjective",
    "difficulty": "medium",
    "Lesson_no": 5,
    "when_to_say": "when showing or expressing concern for others",
    "example": "She was solicitous about his health after he had been sick for days."
  },
  {
    "id": "193",
    "word": "perfunctory",
    "pronunciation": "per-FUNK-tor-ee",
    "meaning": "done without real interest, feeling, or effort",
    "part_of_speech": "adjective",
    "difficulty": "medium",
    "Lesson_no": 6,
    "when_to_say": "when describing something done with little enthusiasm or effort",
    "example": "His perfunctory response showed that he wasn’t really paying attention."
  },
  {
    "id": "194",
    "word": "panacea",
    "pronunciation": "pan-uh-SEE-uh",
    "meaning": "a universal remedy or solution for all problems",
    "part_of_speech": "noun",
    "difficulty": "medium",
    "Lesson_no": 10,
    "when_to_say": "when referring to a supposed solution that can fix all problems",
    "example": "Many people believe that technology is a panacea for all societal issues."
  },
  {
    "id": "195",
    "word": "deference",
    "pronunciation": "DEF-er-uhns",
    "meaning": "respect and esteem due to a superior or elder",
    "part_of_speech": "noun",
    "difficulty": "medium",
    "Lesson_no": 4,
    "when_to_say": "when showing respect or submission to someone in authority",
    "example": "He showed deference to his parents by always listening to their advice."
  },
  {
    "id": "196",
    "word": "intransigent",
    "pronunciation": "in-TRAN-si-juhnt",
    "meaning": "unwilling to change one's views or to agree about something",
    "part_of_speech": "adjective",
    "difficulty": "medium",
    "Lesson_no": 9,
    "when_to_say": "when describing someone who is stubborn or refuses to compromise",
    "example": "The intransigent leader refused to consider any other solutions."
  },

  {
    "id": "197",
    "word": "complacent",
    "pronunciation": "kum-PLAYS-uhnt",
    "meaning": "showing smug or uncritical satisfaction with oneself or one's achievements",
    "part_of_speech": "adjective",
    "difficulty": "medium",
    "Lesson_no": 5,
    "when_to_say": "when someone is overly self-satisfied and unaware of potential risks",
    "example": "He became complacent after winning a few games and stopped practicing."
  },
  {
    "id": "198",
    "word": "epitome",
    "pronunciation": "ih-PIT-uh-mee",
    "meaning": "a perfect example of a particular quality or type",
    "part_of_speech": "noun",
    "difficulty": "medium",
    "Lesson_no": 4,
    "when_to_say": "when describing something that represents a perfect example of a particular quality",
    "example": "She is the epitome of kindness and generosity."
  },
  {
    "id": "199",
    "word": "quixotic",
    "pronunciation": "kwik-SOT-ik",
    "meaning": "exceedingly idealistic; unrealistic and impractical",
    "part_of_speech": "adjective",
    "difficulty": "medium",
    "Lesson_no": 7,
    "when_to_say": "when describing someone or something that is overly idealistic and impractical",
    "example": "His quixotic plan to save the world was doomed to fail."
  },
  {
    "id": "200",
    "word": "rejuvenate",
    "pronunciation": "ri-JOO-vuh-nayt",
    "meaning": "to make someone or something look or feel younger, fresher, or more lively",
    "part_of_speech": "verb",
    "difficulty": "medium",
    "Lesson_no": 8,
    "when_to_say": "when describing the act of restoring vitality or youthfulness",
    "example": "The spa treatments were designed to rejuvenate both body and mind."
  },
  {
    "id": "201",
    "word": "perspicuity",
    "pronunciation": "per-spi-KYOO-ih-tee",
    "meaning": "clarity, being clear and easy to understand",
    "part_of_speech": "noun",
    "difficulty": "medium",
    "Lesson_no": 9,
    "when_to_say": "when describing something that is clear and easily understood",
    "example": "The professor’s perspicuity made complex topics easy to grasp."
  },
  {
    "id": "202",
    "word": "transient",
    "pronunciation": "TRAN-shuhnt",
    "meaning": "lasting only for a short time",
    "part_of_speech": "adjective",
    "difficulty": "medium",
    "Lesson_no": 7,
    "when_to_say": "when describing something that does not last for long",
    "example": "The transient beauty of the rainbow disappeared as quickly as it appeared."
  },
  {
    "id": "203",
    "word": "assiduous",
    "pronunciation": "uh-SID-yoo-uhs",
    "meaning": "showing great care and perseverance",
    "part_of_speech": "adjective",
    "difficulty": "medium",
    "Lesson_no": 5,
    "when_to_say": "when describing someone who is hardworking and diligent",
    "example": "Her assiduous work ethic earned her a promotion."
  },
  {
    "id": "204",
    "word": "harbinger",
    "pronunciation": "HAHR-bin-jer",
    "meaning": "a person or thing that announces or signals the approach of another",
    "part_of_speech": "noun",
    "difficulty": "medium",
    "Lesson_no": 9,
    "when_to_say": "when referring to something or someone that indicates what is to come",
    "example": "The robin is often seen as a harbinger of spring."
  },
  {
    "id": "205",
    "word": "inexorable",
    "pronunciation": "in-EK-sor-uh-bul",
    "meaning": "impossible to stop or prevent",
    "part_of_speech": "adjective",
    "difficulty": "medium",
    "Lesson_no": 10,
    "when_to_say": "when describing something that cannot be changed or avoided",
    "example": "The inexorable rise of technology continues to reshape society."
  },
  {
    "id": "206",
    "word": "pensive",
    "pronunciation": "PEN-siv",
    "meaning": "engaged in serious thought",
    "part_of_speech": "adjective",
    "difficulty": "medium",
    "Lesson_no": 6,
    "when_to_say": "when someone is deep in thought or reflecting",
    "example": "She had a pensive expression on her face as she stared out the window."
  },
  {
    "id": "207",
    "word": "succinct",
    "pronunciation": "suh-KINGKT",
    "meaning": "briefly and clearly expressed",
    "part_of_speech": "adjective",
    "difficulty": "medium",
    "Lesson_no": 8,
    "when_to_say": "when describing something that is concise and to the point",
    "example": "His succinct explanation made it easy for everyone to understand."
  },
  {
    "id": "208",
    "word": "pulchritude",
    "pronunciation": "PUL-kri-tood",
    "meaning": "physical beauty",
    "part_of_speech": "noun",
    "difficulty": "medium",
    "Lesson_no": 10,
    "when_to_say": "when referring to someone’s physical beauty",
    "example": "Her pulchritude was admired by all who met her."
  },
  {
    "id": "209",
    "word": "sophomoric",
    "pronunciation": "soph-uh-MOR-ik",
    "meaning": "pretentious or juvenile; relating to or characteristic of a sophomore",
    "part_of_speech": "adjective",
    "difficulty": "medium",
    "Lesson_no": 6,
    "when_to_say": "when describing someone or something that is immature or overconfident in a foolish way",
    "example": "His sophomoric remarks showed that he still had a lot to learn."
  },
  {
    "id": "210",
    "word": "intermittent",
    "pronunciation": "in-ter-MIT-uhnt",
    "meaning": "occurring at irregular intervals; not continuous or steady",
    "part_of_speech": "adjective",
    "difficulty": "medium",
    "Lesson_no": 9,
    "when_to_say": "when describing something that stops and starts repeatedly",
    "example": "The intermittent rain made it difficult to plan outdoor activities."
  },
  {
    "id": "211",
    "word": "noxious",
    "pronunciation": "NOK-shus",
    "meaning": "harmful, poisonous, or very unpleasant",
    "part_of_speech": "adjective",
    "difficulty": "medium",
    "Lesson_no": 7,
    "when_to_say": "when describing something that is harmful or toxic",
    "example": "The noxious fumes from the factory polluted the air."
  },
  {
    "id": "212",
    "word": "gregarious",
    "pronunciation": "gri-GAIR-ee-uhs",
    "meaning": "fond of company; sociable",
    "part_of_speech": "adjective",
    "difficulty": "medium",
    "Lesson_no": 5,
    "when_to_say": "when describing someone who enjoys being around people",
    "example": "He was a gregarious person who loved meeting new people."
  },
  {
    "id": "213",
    "word": "acumen",
    "pronunciation": "AK-yoo-men",
    "meaning": "the ability to make good judgments and quick decisions",
    "part_of_speech": "noun",
    "difficulty": "medium",
    "Lesson_no": 8,
    "when_to_say": "when referring to someone’s sharp insight or judgment",
    "example": "Her business acumen helped her build a successful company."
  },
  {
    "id": "214",
    "word": "virulent",
    "pronunciation": "VIR-yuh-luhnt",
    "meaning": "extremely severe or harmful in its effects",
    "part_of_speech": "adjective",
    "difficulty": "medium",
    "Lesson_no": 6,
    "when_to_say": "when describing something that is harmful or dangerous in an extreme way",
    "example": "The virus was virulent and spread quickly across the region."
  },
  {
    "id": "215",
    "word": "insidious",
    "pronunciation": "in-SID-ee-uhs",
    "meaning": "proceeding in a gradual, subtle way but with harmful effects",
    "part_of_speech": "adjective",
    "difficulty": "medium",
    "Lesson_no": 9,
    "when_to_say": "when describing something that develops gradually and secretly but is harmful",
    "example": "The insidious effects of smoking may not be immediately apparent."
  },
  {
    "id": "216",
    "word": "harangue",
    "pronunciation": "huh-RANG",
    "meaning": "a lengthy and aggressive speech",
    "part_of_speech": "noun",
    "difficulty": "medium",
    "Lesson_no": 7,
    "when_to_say": "when referring to a long, aggressive, and critical speech",
    "example": "The politician delivered a harangue on the evils of corruption."
  },
  {
    "id": "217",
    "word": "taciturn",
    "pronunciation": "TAS-ih-turn",
    "meaning": "reserved or uncommunicative in speech; saying little",
    "part_of_speech": "adjective",
    "difficulty": "medium",
    "Lesson_no": 8,
    "when_to_say": "when describing someone who is quiet or reluctant to talk",
    "example": "The taciturn man rarely spoke at the meetings."
  },
  {
    "id": "218",
    "word": "vindicate",
    "pronunciation": "VIN-di-kayt",
    "meaning": "to clear someone of blame or suspicion",
    "part_of_speech": "verb",
    "difficulty": "medium",
    "Lesson_no": 10,
    "when_to_say": "when someone is proven to be innocent or justified",
    "example": "The new evidence will vindicate the accused man."
  },
  {
    "id": "219",
    "word": "cacophony",
    "pronunciation": "ka-KAW-fuh-nee",
    "meaning": "a harsh, discordant mixture of sounds",
    "part_of_speech": "noun",
    "difficulty": "medium",
    "Lesson_no": 9,
    "when_to_say": "when describing a loud, jarring noise",
    "example": "The cacophony of car horns in the city was unbearable."
  },
  {
    "id": "220",
    "word": "trepidation",
    "pronunciation": "trep-i-DAY-shun",
    "meaning": "a feeling of fear or agitation about something that may happen",
    "part_of_speech": "noun",
    "difficulty": "medium",
    "Lesson_no": 5,
    "when_to_say": "when referring to a feeling of anxiety or fear about something uncertain",
    "example": "She entered the room with trepidation, unsure of what to expect."
  },
  {
    "id": "221",
    "word": "ameliorate",
    "pronunciation": "uh-MEEL-yuh-rate",
    "meaning": "to make something better or more tolerable",
    "part_of_speech": "verb",
    "difficulty": "medium",
    "Lesson_no": 8,
    "when_to_say": "when trying to improve or make a situation better",
    "example": "The government implemented new policies to ameliorate the economic crisis."
  },
  {
    "id": "222",
    "word": "lament",
    "pronunciation": "luh-MENT",
    "meaning": "to mourn or express sorrow for something",
    "part_of_speech": "verb",
    "difficulty": "medium",
    "Lesson_no": 6,
    "when_to_say": "when expressing sadness or sorrow about something",
    "example": "They lamented the loss of their beloved pet."
  },
  {
    "id": "223",
    "word": "dormant",
    "pronunciation": "DOR-muhnt",
    "meaning": "inactive, in a state of rest or sleep",
    "part_of_speech": "adjective",
    "difficulty": "medium",
    "Lesson_no": 7,
    "when_to_say": "when describing something that is temporarily inactive or not functioning",
    "example": "The volcano has been dormant for over a century."
  },
  {
    "id": "224",
    "word": "delineate",
    "pronunciation": "di-LIN-ee-ayt",
    "meaning": "to describe or portray something precisely",
    "part_of_speech": "verb",
    "difficulty": "medium",
    "Lesson_no": 10,
    "when_to_say": "when describing something in a detailed and clear manner",
    "example": "The architect delineated the plans for the new building."
  },
  {
    "id": "225",
    "word": "supercilious",
    "pronunciation": "soo-per-SIL-ee-us",
    "meaning": "behaving or looking as though one thinks one is superior to others",
    "part_of_speech": "adjective",
    "difficulty": "medium",
    "Lesson_no": 8,
    "when_to_say": "when describing someone who is arrogantly superior",
    "example": "The supercilious manager looked down on his employees."
  },
  {
    "id": "226",
    "word": "cogent",
    "pronunciation": "KO-juhnt",
    "meaning": "clear, logical, and convincing",
    "part_of_speech": "adjective",
    "difficulty": "medium",
    "Lesson_no": 5,
    "when_to_say": "when referring to something that is persuasive and well-reasoned",
    "example": "His cogent argument won over even the skeptics."
  },
  {
    "id": "227",
    "word": "conundrum",
    "pronunciation": "kuh-NUN-druhm",
    "meaning": "a confusing and difficult problem or question",
    "part_of_speech": "noun",
    "difficulty": "medium",
    "Lesson_no": 9,
    "when_to_say": "when describing a problem that is difficult to solve or understand",
    "example": "The puzzle was a conundrum that took hours to solve."
  },
  {
    "id": "228",
    "word": "laconic",
    "pronunciation": "luh-KON-ik",
    "meaning": "using few words; concise",
    "part_of_speech": "adjective",
    "difficulty": "medium",
    "Lesson_no": 6,
    "when_to_say": "when describing a person or style that is brief and to the point",
    "example": "His laconic response left no room for further discussion."
  },
  {
    "id": "229",
    "word": "insipid",
    "pronunciation": "in-SIP-id",
    "meaning": "lacking flavor or interest; dull",
    "part_of_speech": "adjective",
    "difficulty": "medium",
    "Lesson_no": 10,
    "when_to_say": "when describing something that is bland or uninteresting",
    "example": "The soup was insipid and lacked any real flavor."
  },
  {
    "id": "230",
    "word": "euphemism",
    "pronunciation": "YOO-fuh-miz-uhm",
    "meaning": "a mild or indirect word or expression substituted for one considered too harsh or blunt",
    "part_of_speech": "noun",
    "difficulty": "medium",
    "Lesson_no": 5,
    "when_to_say": "when substituting a more polite or mild expression for something harsh",
    "example": "Saying 'passed away' instead of 'died' is a common euphemism."
  },
  {
    "id": "231",
    "word": "recalcitrant",
    "pronunciation": "ri-KAL-sit-ruhnt",
    "meaning": "having an obstinately uncooperative attitude",
    "part_of_speech": "adjective",
    "difficulty": "medium",
    "Lesson_no": 9,
    "when_to_say": "when describing someone who is stubbornly disobedient or uncooperative",
    "example": "The recalcitrant student refused to follow the rules."
  },
  {
    "id": "232",
    "word": "proclivity",
    "pronunciation": "proh-KLIV-ih-tee",
    "meaning": "a tendency to choose or do something regularly",
    "part_of_speech": "noun",
    "difficulty": "medium",
    "Lesson_no": 6,
    "when_to_say": "when describing someone's natural inclination or habit",
    "example": "He has a proclivity for procrastination."
  },
  {
    "id": "233",
    "word": "mitigate",
    "pronunciation": "MIT-ih-gayt",
    "meaning": "to make something less severe, serious, or painful",
    "part_of_speech": "verb",
    "difficulty": "medium",
    "Lesson_no": 8,
    "when_to_say": "when reducing the severity or intensity of something",
    "example": "The doctor gave her medication to mitigate the pain."
  },
  {
    "id": "234",
    "word": "belligerent",
    "pronunciation": "buh-LIJ-er-uhnt",
    "meaning": "hostile and aggressive",
    "part_of_speech": "adjective",
    "difficulty": "medium",
    "Lesson_no": 7,
    "when_to_say": "when describing someone who is angry or eager to argue or fight",
    "example": "The belligerent man started a fight at the bar."
  },
  {
    "id": "235",
    "word": "ephemeral",
    "pronunciation": "ih-FEM-er-uhl",
    "meaning": "lasting for a very short time",
    "part_of_speech": "adjective",
    "difficulty": "medium",
    "Lesson_no": 5,
    "when_to_say": "when referring to something that is fleeting or short-lived",
    "example": "The beauty of the sunset was ephemeral, lasting only a few minutes."
  },
  {
    "id": "236",
    "word": "equanimity",
    "pronunciation": "ek-wuh-NIM-ih-tee",
    "meaning": "mental calmness, especially in difficult situations",
    "part_of_speech": "noun",
    "difficulty": "medium",
    "Lesson_no": 10,
    "when_to_say": "when describing someone who is calm and composed under pressure",
    "example": "She faced the crisis with equanimity, remaining calm throughout."
  },

  {
    "id": "237",
    "word": "profound",
    "pronunciation": "pruh-FOUND",
    "meaning": "having deep meaning or insight",
    "part_of_speech": "adjective",
    "difficulty": "medium",
    "Lesson_no": 7,
    "when_to_say": "when describing something with deep significance or impact",
    "example": "His profound thoughts on philosophy were admired by everyone."
  },
  {
    "id": "238",
    "word": "ameliorate",
    "pronunciation": "uh-MEE-lee-uh-rate",
    "meaning": "to make something better or more tolerable",
    "part_of_speech": "verb",
    "difficulty": "medium",
    "Lesson_no": 8,
    "when_to_say": "when describing actions to improve a situation",
    "example": "The new regulations aim to ameliorate air quality."
  },
  {
    "id": "239",
    "word": "antithesis",
    "pronunciation": "an-TITH-uh-sis",
    "meaning": "a direct contrast or opposite of something",
    "part_of_speech": "noun",
    "difficulty": "medium",
    "Lesson_no": 9,
    "when_to_say": "when comparing two things that are opposites",
    "example": "Her calm demeanor was the antithesis of his frantic behavior."
  },
  {
    "id": "240",
    "word": "benevolent",
    "pronunciation": "buh-NEV-uh-luhnt",
    "meaning": "showing kindness or goodwill",
    "part_of_speech": "adjective",
    "difficulty": "medium",
    "Lesson_no": 10,
    "when_to_say": "when describing someone who is kind and generous",
    "example": "The benevolent woman donated a large sum to the charity."
  },
  {
    "id": "241",
    "word": "cognizant",
    "pronunciation": "KOG-ni-zuhnt",
    "meaning": "aware or conscious of something",
    "part_of_speech": "adjective",
    "difficulty": "medium",
    "Lesson_no": 5,
    "when_to_say": "when being aware of something",
    "example": "She was cognizant of the risks involved in the decision."
  },
  {
    "id": "242",
    "word": "quixotic",
    "pronunciation": "kwik-SOT-ik",
    "meaning": "extremely idealistic; unrealistic and impractical",
    "part_of_speech": "adjective",
    "difficulty": "medium",
    "Lesson_no": 6,
    "when_to_say": "when describing someone with impractical ideas",
    "example": "His quixotic plan to change the world was met with skepticism."
  },
  {
    "id": "243",
    "word": "vicarious",
    "pronunciation": "vi-KAIR-ee-uhs",
    "meaning": "experienced in the imagination through the feelings or actions of another person",
    "part_of_speech": "adjective",
    "difficulty": "medium",
    "Lesson_no": 8,
    "when_to_say": "when feeling or living something through another person",
    "example": "She felt a vicarious thrill watching her son win the race."
  },
  {
    "id": "244",
    "word": "cynical",
    "pronunciation": "SIN-i-kul",
    "meaning": "believing that people are motivated purely by self-interest; distrustful of human sincerity",
    "part_of_speech": "adjective",
    "difficulty": "medium",
    "Lesson_no": 7,
    "when_to_say": "when describing someone who is distrustful or skeptical about others' motives",
    "example": "He had a cynical view of politics, believing that no politician could be trusted."
  },
  {
    "id": "245",
    "word": "reverent",
    "pronunciation": "REV-er-uhnt",
    "meaning": "showing deep respect or reverence",
    "part_of_speech": "adjective",
    "difficulty": "medium",
    "Lesson_no": 9,
    "when_to_say": "when showing respect or admiration for something",
    "example": "The reverent silence in the church was a testament to the solemn occasion."
  },
  {
    "id": "246",
    "word": "profound",
    "pronunciation": "pruh-FOUND",
    "meaning": "having deep meaning or insight",
    "part_of_speech": "adjective",
    "difficulty": "medium",
    "Lesson_no": 8,
    "when_to_say": "when describing something with deep impact",
    "example": "His profound knowledge of history impressed the scholars."
  },
  {
    "id": "247",
    "word": "perfunctory",
    "pronunciation": "per-FUNK-tuh-ree",
    "meaning": "carried out with minimal effort or reflection",
    "part_of_speech": "adjective",
    "difficulty": "medium",
    "Lesson_no": 6,
    "when_to_say": "when describing something done in a routine or superficial manner",
    "example": "Her perfunctory response showed that she was not really interested in the topic."
  },
  {
    "id": "248",
    "word": "nadir",
    "pronunciation": "NAY-der",
    "meaning": "the lowest point in a person's life or career",
    "part_of_speech": "noun",
    "difficulty": "medium",
    "Lesson_no": 10,
    "when_to_say": "when referring to the lowest point of something",
    "example": "The company's bankruptcy marked the nadir of its financial troubles."
  },
  {
    "id": "249",
    "word": "opulent",
    "pronunciation": "OP-yuh-luhnt",
    "meaning": "rich and luxurious in appearance or quality",
    "part_of_speech": "adjective",
    "difficulty": "medium",
    "Lesson_no": 9,
    "when_to_say": "when describing something lavish or wealthy",
    "example": "The opulent mansion featured marble floors and chandeliers."
  },
  {
    "id": "250",
    "word": "juxtapose",
    "pronunciation": "JUK-stuh-POHZ",
    "meaning": "to place two or more things side by side for comparison",
    "part_of_speech": "verb",
    "difficulty": "medium",
    "Lesson_no": 7,
    "when_to_say": "when comparing two or more things by placing them next to each other",
    "example": "The artist juxtaposed bright colors with dark shadows to create contrast."
  }
]
